lixinapi/__config.py
lixinapi/__init__.py
lixinapi/login.py
lixinapi/secret.py
lixinapi/stock/__init__.py
lixinapi/stock/lixin.py
lixinAPI-1.0.3.dist-info/METADATA
lixinAPI-1.0.3.dist-info/WHEEL
lixinAPI-1.0.3.dist-info/top_level.txt
lixinAPI-1.0.3.dist-info/RECORD
