Metadata-Version: 2.1
Name: lixinAPI
Version: 1.0.3
Summary: A small example package
Home-page: https://github.com/PepperPapa/xinNotes
Author: zhangq
Author-email: 569535175@qq.com
License: UNKNOWN
Platform: UNKNOWN
Requires-Dist: requests
